pynetdot
pynetdot/models
