Metadata-Version: 1.1
Name: pynetdot
Version: 1.5.1
Summary: Python client for netdot REST API
Home-page: https://github.com/ArnesSI/pynetdot
Author: Matej Vadnjal
Author-email: matej.vadnjal@arnes.si
License: LGPLv3
Platform: UNKNOWN
Classifier: Development Status :: 4 - Beta
Classifier: Intended Audience :: Developers
Classifier: Intended Audience :: System Administrators
Classifier: Intended Audience :: Telecommunications Industry
Classifier: License :: OSI Approved :: GNU Lesser General Public License v3 (LGPLv3)
Classifier: Programming Language :: Python :: 2
Classifier: Programming Language :: Python :: 3
Requires: dateutil
Requires: requests
Requires: yaml
Requires: future
